_compintpy.cpython-314-x86_64-linux-gnu.so
compintpy/__init__.py
compintpy/elias.py
compintpy.libs/libgomp-e985bcbb.so.1.0.0
compintpy-0.0.5.dist-info/METADATA
compintpy-0.0.5.dist-info/WHEEL
compintpy-0.0.5.dist-info/top_level.txt
compintpy-0.0.5.dist-info/RECORD
compintpy-0.0.5.dist-info/licenses/LICENSE
