Metadata-Version: 2.4
Name: compintpy
Version: 0.0.5
Summary: Python bindings for compintc: A variable length compression algorithm.
Home-page: https://github.com/JeffWigger/compintpy
Author: Jeffrey Wigger
License: BSD-3-Clause
Requires-Python: >=3.9
License-File: LICENSE
Requires-Dist: numpy
Provides-Extra: test
Requires-Dist: pytest>=6.0; extra == "test"
Dynamic: author
Dynamic: description
Dynamic: description-content-type
Dynamic: home-page
Dynamic: license
Dynamic: license-file
Dynamic: provides-extra
Dynamic: requires-dist
Dynamic: requires-python
Dynamic: summary
